llm_lambda_labs.py
llm_lambda_labs-0.2.dist-info/LICENSE
llm_lambda_labs-0.2.dist-info/METADATA
llm_lambda_labs-0.2.dist-info/WHEEL
llm_lambda_labs-0.2.dist-info/entry_points.txt
llm_lambda_labs-0.2.dist-info/top_level.txt
llm_lambda_labs-0.2.dist-info/RECORD
