Metadata-Version: 2.2
Name: llm-lambda-labs
Version: 0.2
Summary: Run prompts against LLMs hosted by https://lambdalabs.com/
Author: Simon Willison
License: Apache-2.0
Project-URL: Homepage, https://github.com/simonw/llm-lambda-labs
Project-URL: Changelog, https://github.com/simonw/llm-lambda-labs/releases
Project-URL: Issues, https://github.com/simonw/llm-lambda-labs/issues
Project-URL: CI, https://github.com/simonw/llm-lambda-labs/actions
Classifier: License :: OSI Approved :: Apache Software License
Requires-Python: >=3.9
License-File: LICENSE
Requires-Dist: llm>=0.22
Requires-Dist: httpx
Requires-Dist: httpx-sse
Provides-Extra: test
Requires-Dist: pytest; extra == "test"
Requires-Dist: pytest-recording; extra == "test"
Requires-Dist: pytest-asyncio; extra == "test"
